datasette_cluster_map/__init__.py
datasette_cluster_map/static/datasette-cluster-map.js
datasette_cluster_map/static/leaflet.markercluster.css
datasette_cluster_map/static/leaflet.markercluster.js
datasette_cluster_map/static/leaflet.markercluster.min.js
datasette_cluster_map-0.18.2.dist-info/LICENSE
datasette_cluster_map-0.18.2.dist-info/METADATA
datasette_cluster_map-0.18.2.dist-info/WHEEL
datasette_cluster_map-0.18.2.dist-info/entry_points.txt
datasette_cluster_map-0.18.2.dist-info/top_level.txt
datasette_cluster_map-0.18.2.dist-info/RECORD
