Metadata-Version: 2.1
Name: datasette-cluster-map
Version: 0.18.2
Summary: Datasette plugin that shows a map for any data with latitude/longitude columns
Home-page: https://github.com/simonw/datasette-cluster-map
Author: Simon Willison
License: Apache License, Version 2.0
Project-URL: Issues, https://github.com/simonw/datasette-cluster-map/issues
Project-URL: CI, https://github.com/simonw/datasette-cluster-map/actions
Project-URL: Changelog, https://github.com/simonw/datasette-cluster-map/releases
Classifier: Framework :: Datasette
Classifier: License :: OSI Approved :: Apache Software License
Requires-Python: >=3.8
License-File: LICENSE
Requires-Dist: datasette >=0.54
Requires-Dist: datasette-leaflet >=0.2.2
Provides-Extra: playwright
Requires-Dist: pytest-playwright ; extra == 'playwright'
Provides-Extra: test
Requires-Dist: pytest ; extra == 'test'
Requires-Dist: pytest-asyncio ; extra == 'test'
Requires-Dist: httpx ; extra == 'test'
Requires-Dist: sqlite-utils ; extra == 'test'
Requires-Dist: nest-asyncio ; extra == 'test'
Requires-Dist: datasette-test ; extra == 'test'
